dcat_ap_hub/__init__.py
dcat_ap_hub/py.typed
dcat_ap_hub/core/dataset.py
dcat_ap_hub/core/files.py
dcat_ap_hub/core/interfaces.py
dcat_ap_hub/internals/integrations.py
dcat_ap_hub/internals/loaders.py
dcat_ap_hub/internals/logging.py
dcat_ap_hub/internals/models.py
dcat_ap_hub/internals/parser.py
dcat_ap_hub/internals/processor.py
dcat_ap_hub/internals/transfer.py
dcat_ap_hub-0.1.1.dist-info/METADATA
dcat_ap_hub-0.1.1.dist-info/WHEEL
dcat_ap_hub-0.1.1.dist-info/licenses/LICENSE
dcat_ap_hub-0.1.1.dist-info/RECORD
