Metadata-Version: 2.4
Name: dcat-ap-hub
Version: 0.1.1
Summary: A library for loading datasets and models whose metadata is provided in the DCAT-AP format.
Author-email: maxbrzr <maximilian.burzer@kit.edu>
License-File: LICENSE
Requires-Python: >=3.11
Requires-Dist: accelerate>=1.12.0
Requires-Dist: beautifulsoup4>=4.13.5
Requires-Dist: chardet>=5.2.0
Requires-Dist: ipykernel>=6.30.0
Requires-Dist: opencv-python>=4.12.0.88
Requires-Dist: openpyxl>=3.1.5
Requires-Dist: pandas-stubs>=2.3.0.250703
Requires-Dist: pandas>=2.3.1
Requires-Dist: pypdf>=6.1.0
Requires-Dist: rdflib>=7.1.4
Requires-Dist: requests>=2.32.4
Requires-Dist: torch>=2.9.0
Requires-Dist: tqdm>=4.67.1
Requires-Dist: transformers>=4.57.1
Requires-Dist: types-requests>=2.32.4.20250611
Requires-Dist: types-tqdm>=4.67.0.20250516
